[
    {
        "src": "https://fastly.picsum.photos/id/978/750/350.jpg?hmac=LMbL30hMEG1ibofLPaNFakB68_vCBcGxuNo3PA849kA",
        "title": "TEST",
        "url": "https://www.google.com"
    },
    {
        "src": "https://fastly.picsum.photos/id/502/750/300.jpg?hmac=wRc06tbUcGbvxYm1NXyO9f4gVDJD62eym-orH6tVx3o",
        "title": "TEST",
        "url": "#"
    },
    {
        "src": "https://fastly.picsum.photos/id/220/750/300.jpg?hmac=DCEYZsKfmdmfAVQP668d9zAm5h7Xl4RZ9TdEg-T0mHU",
        "title": "TEST",
        "url": ""
    },
    {
        "src": "https://fastly.picsum.photos/id/428/750/300.jpg?hmac=Ebu_j9GgqOtuBnGAXev9xI5FnPFOAoz5HKBpVfyy-xM",
        "title": "TEST",
        "url": "https://www.google.com"
    },
    {
        "src": "https://fastly.picsum.photos/id/315/750/300.jpg?hmac=Q4pwQY0pGeElqfMHzRxymMvKQM7_yS03CWoLieyqUPg",
        "title": "TEST",
        "url": "https://www.google.com"
    },
    {
        "src": "https://fastly.picsum.photos/id/634/750/300.jpg?hmac=80mvOCnydT3MVh8h7onxjlOcicLhmSgCwYKdv-CLFyU",
        "title": "TEST",
        "url": "https://www.google.com"
    },
    {
        "src": "https://fastly.picsum.photos/id/388/2048/1366.jpg?hmac=L-XZPxffbJTrN-AqyXnE6o8XCgs9fFC4REGSDpY9Ols",
        "title": "TEST",
        "url": "https://www.google.com"
    }
]
